concat_map/__init__.py
concat_map/concat.py
concat_map-0.1.2.dist-info/LICENSE
concat_map-0.1.2.dist-info/METADATA
concat_map-0.1.2.dist-info/WHEEL
concat_map-0.1.2.dist-info/top_level.txt
concat_map-0.1.2.dist-info/RECORD
