Metadata-Version: 2.1
Name: concat_map
Version: 0.1.2
Summary: A module for accessing many array-like objects as if they are one array.
Author: Gary William Flake
Author-email: gary@flake.org
Classifier: Programming Language :: Python :: 3
Classifier: License :: OSI Approved :: MIT License
Classifier: Operating System :: OS Independent
License-File: LICENSE
